PyMoments/Combinatorics.py
PyMoments/DataStructures.py
PyMoments/Moments.py
PyMoments/__init__.py
tests/__init__.py
tests/test_combinatorics.py
tests/test_intPartitionTree.py
tests/test_moments.py
tests/data/test_10path_data.csv
tests/data/test_10path_tests.csv
PyMoments-1.0.1.dist-info/METADATA
PyMoments-1.0.1.dist-info/WHEEL
PyMoments-1.0.1.dist-info/top_level.txt
PyMoments-1.0.1.dist-info/RECORD
