Metadata-Version: 2.1
Name: PyMoments
Version: 1.0.1
Summary: Unbiased estimators for multivariate statistical moments
Home-page: https://github.com/KevinDalySmith/PyMoments
Author: Kevin D. Smith
Author-email: kevinsmith@ucsb.edu
License: CC BY-NC 4.0
Keywords: statistics
Platform: UNKNOWN
Classifier: Development Status :: 3 - Alpha
Classifier: Programming Language :: Python :: 3
Classifier: Programming Language :: Python :: 3.7
Classifier: Intended Audience :: Science/Research
Classifier: Topic :: Scientific/Engineering :: Mathematics
Requires-Dist: numpy
